famudy/__init__.py
famudy/constants.py
famudy/env_data.py
famudy/config/__init__.py
famudy/config/bbox.py
famudy/config/model/__init__.py
famudy/config/model/flame.py
famudy/config/run/__init__.py
famudy/config/run/calibration.py
famudy/config/run/calibration_params.py
famudy/data/__init__.py
famudy/data/capture_data_processed.py
famudy/data/capture_data_processed_v2.py
famudy/models/__init__.py
famudy/models/flame.py
famudy/provider/__init__.py
famudy/provider/expression_animation_provider.py
famudy/provider/flame_provider.py
famudy/provider/mesh_provider.py
famudy/provider/nphm_provider.py
famudy/util/__init__.py
famudy/util/quantization.py
famudy_data-0.0.7.dist-info/METADATA
famudy_data-0.0.7.dist-info/WHEEL
famudy_data-0.0.7.dist-info/top_level.txt
famudy_data-0.0.7.dist-info/RECORD
