Metadata-Version: 2.1
Name: famudy-data
Version: 0.0.7
Summary: <<<ENTER_DESCRIPTION>>>
Author-email: Tobias Kirschstein <tobias.kirschstein@gmail.com>
License: Apache 2.0
Classifier: Development Status :: 3 - Alpha
Classifier: Programming Language :: Python :: 3
Classifier: Operating System :: OS Independent
Requires-Python: >=3.8.0
Requires-Dist: open3d
Requires-Dist: trimesh
Requires-Dist: environs
Requires-Dist: elias
Requires-Dist: tyro
Requires-Dist: dreifus
Requires-Dist: pandas
Requires-Dist: python-openctm
Requires-Dist: smplx
Requires-Dist: numpy <=1.23.1
Requires-Dist: chumpy
Provides-Extra: dev
